keg_auth/__init__.py
keg_auth/cli.py
keg_auth/core.py
keg_auth/extensions.py
keg_auth/forms.py
keg_auth/grids.py
keg_auth/mail.py
keg_auth/testing.py
keg_auth/version.py
keg_auth/views.py
keg_auth/i18n/babel.cfg
keg_auth/i18n/keg_auth.pot
keg_auth/i18n/es/LC_MESSAGES/keg_auth.mo
keg_auth/i18n/es/LC_MESSAGES/keg_auth.po
keg_auth/libs/__init__.py
keg_auth/libs/authenticators.py
keg_auth/libs/decorators.py
keg_auth/libs/navigation.py
keg_auth/libs/templates.py
keg_auth/model/__init__.py
keg_auth/model/entity_registry.py
keg_auth/model/types.py
keg_auth/model/utils.py
keg_auth/static/i18n/es/LC_MESSAGES/keg_auth.json
keg_auth/templates/keg-auth/crud-addedit.html
keg_auth/templates/keg-auth/crud-list.html
keg_auth/templates/keg-auth/flash-messages-only.html
keg_auth/templates/keg-auth/forgot-password.html
keg_auth/templates/keg-auth/i18n.j2
keg_auth/templates/keg-auth/login.html
keg_auth/templates/keg-auth/multi-part-mail.j2
keg_auth/templates/keg-auth/navigation.html
keg_auth/templates/keg-auth/new-user-mail.j2
keg_auth/templates/keg-auth/reset-password-mail.j2
keg_auth/templates/keg-auth/set-password.html
keg_auth/tests/__init__.py
keg_auth/tests/conftest.py
keg_auth/tests/test_auth_manager.py
keg_auth/tests/test_authenticators.py
keg_auth/tests/test_cli.py
keg_auth/tests/test_core.py
keg_auth/tests/test_forms.py
keg_auth/tests/test_grids.py
keg_auth/tests/test_mail.py
keg_auth/tests/test_model.py
keg_auth/tests/test_navigation.py
keg_auth/tests/test_utils.py
keg_auth/tests/test_views.py
keg_auth/tests/utils.py
keg_auth_ta/__init__.py
keg_auth_ta/app.py
keg_auth_ta/cli.py
keg_auth_ta/config.py
keg_auth_ta/events.py
keg_auth_ta/extensions.py
keg_auth_ta/grids.py
keg_auth_ta/views.py
keg_auth_ta/model/__init__.py
keg_auth_ta/model/entities.py
keg_auth_ta/templates/base-page.html
keg_auth_ta/templates/base.html
keg_auth_ta/templates/email.j2
keg_auth_ta/templates/home.html
Keg_Auth-0.8.1.dist-info/METADATA
Keg_Auth-0.8.1.dist-info/WHEEL
Keg_Auth-0.8.1.dist-info/top_level.txt
Keg_Auth-0.8.1.dist-info/RECORD
