Metadata-Version: 2.1
Name: Keg-Auth
Version: 0.8.1
Summary: Authentication plugin for Keg
Home-page: https://github.com/level12/keg-auth
Author: Randy Syring
Author-email: randy.syring@level12.io
License: UNKNOWN
Platform: UNKNOWN
Classifier: Development Status :: 4 - Beta
Classifier: Intended Audience :: Developers
Classifier: License :: OSI Approved :: BSD License
Classifier: Operating System :: OS Independent
Classifier: Programming Language :: Python :: 3
Requires-Dist: authlib
Requires-Dist: bcrypt
Requires-Dist: markdown-it-py
Requires-Dist: Flask-Login (>0.4.1)
Requires-Dist: Keg (>=0.11.0)
Requires-Dist: KegElements (>=0.9.0)
Requires-Dist: inflect
Requires-Dist: passlib
Requires-Dist: shortuuid
Requires-Dist: webgrid (>=0.4.13)
Provides-Extra: i18n
Requires-Dist: morphi ; extra == 'i18n'
Requires-Dist: webgrid[i18n] ; extra == 'i18n'
Provides-Extra: jwt
Requires-Dist: flask-jwt-extended (>=4.0.0) ; extra == 'jwt'
Provides-Extra: ldap
Requires-Dist: python-ldap ; extra == 'ldap'
Provides-Extra: mail
Requires-Dist: Flask-Mail ; extra == 'mail'
Provides-Extra: oauth
Requires-Dist: requests ; extra == 'oauth'
Provides-Extra: tests
Requires-Dist: email-validator ; extra == 'tests'
Requires-Dist: flake8 ; extra == 'tests'
Requires-Dist: flask-bootstrap ; extra == 'tests'
Requires-Dist: flask-jwt-extended (>=4.0.0) ; extra == 'tests'
Requires-Dist: flask-mail ; extra == 'tests'
Requires-Dist: flask-webtest ; extra == 'tests'
Requires-Dist: freezegun ; extra == 'tests'
Requires-Dist: mock ; extra == 'tests'
Requires-Dist: psycopg ; extra == 'tests'
Requires-Dist: psycopg-binary ; extra == 'tests'
Requires-Dist: python-ldap (==3.4.3) ; extra == 'tests'
Requires-Dist: pyquery ; extra == 'tests'
Requires-Dist: pytest ; extra == 'tests'
Requires-Dist: pytest-cov ; extra == 'tests'
Requires-Dist: requests ; extra == 'tests'
Requires-Dist: tox ; extra == 'tests'
Requires-Dist: xlsxwriter ; extra == 'tests'
Requires-Dist: validators ; extra == 'tests'
